ETools/__init__.py
ETools/main.py
EToolsbyEndie-1.1.0.dist-info/METADATA
EToolsbyEndie-1.1.0.dist-info/WHEEL
EToolsbyEndie-1.1.0.dist-info/entry_points.txt
EToolsbyEndie-1.1.0.dist-info/top_level.txt
EToolsbyEndie-1.1.0.dist-info/RECORD
