Metadata-Version: 2.1
Name: EToolsbyEndie
Version: 1.1.0
Home-page: https://github.com/realendie/ETools_By_Endie
Author: Wyatt Johnson
Author-email: enderprooffical@gmail.com
License: MIT
Keywords: python,utility,youtube,tools,downloader,video,audio,converter,mp3,mp4,youtube-dl,yt-dlp,ffmpeg
Requires-Dist: darkdetect==0.8.0
Requires-Dist: packaging==24.2
Requires-Dist: yt-dlp
Requires-Dist: ffmpeg
